tsugu_api/__init__.py
tsugu_api/_bandoristation.py
tsugu_api/_station.py
tsugu_api/_tsugu.py
tsugu_api/_user.py
tsugu_api_async/__init__.py
tsugu_api_async/_bandoristation.py
tsugu_api_async/_station.py
tsugu_api_async/_tsugu.py
tsugu_api_async/_user.py
tsugu_api_core/__init__.py
tsugu_api_core/_network.py
tsugu_api_core/_settings.py
tsugu_api_core/_typing.py
tsugu_api_core/exception.py
tsugu_api_core/utils.py
tsugu_api_core/client/__init__.py
tsugu_api_core/client/_client.py
tsugu_api_core/client/aiohttp.py
tsugu_api_core/client/httpx.py
tsugu_api_python-1.5.10.dist-info/licenses/LICENSE
tsugu_api_python-1.5.10.dist-info/METADATA
tsugu_api_python-1.5.10.dist-info/WHEEL
tsugu_api_python-1.5.10.dist-info/top_level.txt
tsugu_api_python-1.5.10.dist-info/RECORD
