Metadata-Version: 2.4
Name: tsugu-api-python
Version: 1.5.10
Summary: Tsugu BanGDream Bot 的功能 API 统合包
Home-page: https://github.com/WindowsSov8forUs/tsugu-api-python
Author: WindowsSov8
Author-email: qwertyuiop2333@hotmail.com
License: MIT
Classifier: Programming Language :: Python :: 3.8
Classifier: License :: OSI Approved :: MIT License
Classifier: Operating System :: OS Independent
Requires-Python: >=3.8
License-File: LICENSE
Requires-Dist: typing_extensions>=4.5.0
Provides-Extra: httpx
Requires-Dist: httpx>=0.22.0; extra == "httpx"
Provides-Extra: aiohttp
Requires-Dist: aiohttp>=3.8.1; extra == "aiohttp"
Dynamic: author
Dynamic: author-email
Dynamic: classifier
Dynamic: description
Dynamic: description-content-type
Dynamic: home-page
Dynamic: license
Dynamic: license-file
Dynamic: provides-extra
Dynamic: requires-dist
Dynamic: requires-python
Dynamic: summary
